ecoact_decarb_project/__init__.py
ecoact_decarb_project/db_model/__init__.py
ecoact_decarb_project/domain_model/__init__.py
ecoact_decarb_project-0.0.1.dist-info/METADATA
ecoact_decarb_project-0.0.1.dist-info/WHEEL
ecoact_decarb_project-0.0.1.dist-info/RECORD
